hash_table_at/__init__.py
hash_table_at/main.py
hash_table_at-0.1.0.dist-info/LICENSE
hash_table_at-0.1.0.dist-info/METADATA
hash_table_at-0.1.0.dist-info/WHEEL
hash_table_at-0.1.0.dist-info/RECORD
