Metadata-Version: 2.1
Name: hash-table-at
Version: 0.1.0
Summary: 
Author: andreatamburri
Author-email: andrea.tamburri@flixbus.com
Requires-Python: >=3.12,<4.0
Classifier: Programming Language :: Python :: 3
Classifier: Programming Language :: Python :: 3.12
